getfilestats/README.md
getfilestats/__init__.py
getfilestats/requirements.txt
getfilestats/thirdparty.json
getfilestats-0.10.dist-info/LICENSE.rst
getfilestats-0.10.dist-info/METADATA
getfilestats-0.10.dist-info/WHEEL
getfilestats-0.10.dist-info/top_level.txt
getfilestats-0.10.dist-info/RECORD
