Metadata-Version: 2.1
Name: getfilestats
Version: 0.10
Summary: Retrieves statistics from files (os.stat) e returns a pandas DataFrame
Home-page: https://github.com/hansalemaos/getfilestats
Author: Johannes Fischer
Author-email: aulasparticularesdealemaosp@gmail.com
License: MIT
Keywords: os.stat,stat,pandas
Classifier: Development Status :: 4 - Beta
Classifier: Programming Language :: Python :: 3 :: Only
Classifier: Programming Language :: Python :: 3.10
Classifier: Topic :: Software Development :: Libraries :: Python Modules
Classifier: Topic :: Utilities
License-File: LICENSE.rst
Requires-Dist: a-pandas-ex-apply-ignore-exceptions
Requires-Dist: a-pandas-ex-horizontal-explode
Requires-Dist: list-all-files-recursively
Requires-Dist: pandas
